[
   {
      "name":"Afghanistan",
      "id":"AF"
   },
   {
      "name":"Åland Islands",
      "id":"AX"
   },
   {
      "name":"Albania",
      "id":"AL"
   },
   {
      "name":"Algeria",
      "id":"DZ"
   },
   {
      "name":"American Samoa",
      "id":"AS"
   },
   {
      "name":"AndorrA",
      "id":"AD"
   },
   {
      "name":"Angola",
      "id":"AO"
   },
   {
      "name":"Anguilla",
      "id":"AI"
   },
   {
      "name":"Antarctica",
      "id":"AQ"
   },
   {
      "name":"Antigua and Barbuda",
      "id":"AG"
   },
   {
      "name":"Argentina",
      "id":"AR"
   },
   {
      "name":"Armenia",
      "id":"AM"
   },
   {
      "name":"Aruba",
      "id":"AW"
   },
   {
      "name":"Australia",
      "id":"AU"
   },
   {
      "name":"Austria",
      "id":"AT"
   },
   {
      "name":"Azerbaijan",
      "id":"AZ"
   },
   {
      "name":"Bahamas",
      "id":"BS"
   },
   {
      "name":"Bahrain",
      "id":"BH"
   },
   {
      "name":"Bangladesh",
      "id":"BD"
   },
   {
      "name":"Barbados",
      "id":"BB"
   },
   {
      "name":"Belarus",
      "id":"BY"
   },
   {
      "name":"Belgium",
      "id":"BE"
   },
   {
      "name":"Belize",
      "id":"BZ"
   },
   {
      "name":"Benin",
      "id":"BJ"
   },
   {
      "name":"Bermuda",
      "id":"BM"
   },
   {
      "name":"Bhutan",
      "id":"BT"
   },
   {
      "name":"Bolivia",
      "id":"BO"
   },
   {
      "name":"Bosnia and Herzegovina",
      "id":"BA"
   },
   {
      "name":"Botswana",
      "id":"BW"
   },
   {
      "name":"Bouvet Island",
      "id":"BV"
   },
   {
      "name":"Brazil",
      "id":"BR"
   },
   {
      "name":"British Indian Ocean Territory",
      "id":"IO"
   },
   {
      "name":"Brunei Darussalam",
      "id":"BN"
   },
   {
      "name":"Bulgaria",
      "id":"BG"
   },
   {
      "name":"Burkina Faso",
      "id":"BF"
   },
   {
      "name":"Burundi",
      "id":"BI"
   },
   {
      "name":"Cambodia",
      "id":"KH"
   },
   {
      "name":"Cameroon",
      "id":"CM"
   },
   {
      "name":"Canada",
      "id":"CA"
   },
   {
      "name":"Cape Verde",
      "id":"CV"
   },
   {
      "name":"Cayman Islands",
      "id":"KY"
   },
   {
      "name":"Central African Republic",
      "id":"CF"
   },
   {
      "name":"Chad",
      "id":"TD"
   },
   {
      "name":"Chile",
      "id":"CL"
   },
   {
      "name":"China",
      "id":"CN"
   },
   {
      "name":"Christmas Island",
      "id":"CX"
   },
   {
      "name":"Cocos (Keeling) Islands",
      "id":"CC"
   },
   {
      "name":"Colombia",
      "id":"CO"
   },
   {
      "name":"Comoros",
      "id":"KM"
   },
   {
      "name":"Congo",
      "id":"CG"
   },
   {
      "name":"Congo, The Democratic Republic of the",
      "id":"CD"
   },
   {
      "name":"Cook Islands",
      "id":"CK"
   },
   {
      "name":"Costa Rica",
      "id":"CR"
   },
   {
      "name":"Cote D\\'Ivoire",
      "id":"CI"
   },
   {
      "name":"Croatia",
      "id":"HR"
   },
   {
      "name":"Cuba",
      "id":"CU"
   },
   {
      "name":"Cyprus",
      "id":"CY"
   },
   {
      "name":"Czech Republic",
      "id":"CZ"
   },
   {
      "name":"Denmark",
      "id":"DK"
   },
   {
      "name":"Djibouti",
      "id":"DJ"
   },
   {
      "name":"Dominica",
      "id":"DM"
   },
   {
      "name":"Dominican Republic",
      "id":"DO"
   },
   {
      "name":"Ecuador",
      "id":"EC"
   },
   {
      "name":"Egypt",
      "id":"EG"
   },
   {
      "name":"El Salvador",
      "id":"SV"
   },
   {
      "name":"Equatorial Guinea",
      "id":"GQ"
   },
   {
      "name":"Eritrea",
      "id":"ER"
   },
   {
      "name":"Estonia",
      "id":"EE"
   },
   {
      "name":"Ethiopia",
      "id":"ET"
   },
   {
      "name":"Falkland Islands (Malvinas)",
      "id":"FK"
   },
   {
      "name":"Faroe Islands",
      "id":"FO"
   },
   {
      "name":"Fiji",
      "id":"FJ"
   },
   {
      "name":"Finland",
      "id":"FI"
   },
   {
      "name":"France",
      "id":"FR"
   },
   {
      "name":"French Guiana",
      "id":"GF"
   },
   {
      "name":"French Polynesia",
      "id":"PF"
   },
   {
      "name":"French Southern Territories",
      "id":"TF"
   },
   {
      "name":"Gabon",
      "id":"GA"
   },
   {
      "name":"Gambia",
      "id":"GM"
   },
   {
      "name":"Georgia",
      "id":"GE"
   },
   {
      "name":"Germany",
      "id":"DE"
   },
   {
      "name":"Ghana",
      "id":"GH"
   },
   {
      "name":"Gibraltar",
      "id":"GI"
   },
   {
      "name":"Greece",
      "id":"GR"
   },
   {
      "name":"Greenland",
      "id":"GL"
   },
   {
      "name":"Grenada",
      "id":"GD"
   },
   {
      "name":"Guadeloupe",
      "id":"GP"
   },
   {
      "name":"Guam",
      "id":"GU"
   },
   {
      "name":"Guatemala",
      "id":"GT"
   },
   {
      "name":"Guernsey",
      "id":"GG"
   },
   {
      "name":"Guinea",
      "id":"GN"
   },
   {
      "name":"Guinea-Bissau",
      "id":"GW"
   },
   {
      "name":"Guyana",
      "id":"GY"
   },
   {
      "name":"Haiti",
      "id":"HT"
   },
   {
      "name":"Heard Island and Mcdonald Islands",
      "id":"HM"
   },
   {
      "name":"Holy See (Vatican City State)",
      "id":"VA"
   },
   {
      "name":"Honduras",
      "id":"HN"
   },
   {
      "name":"Hong Kong",
      "id":"HK"
   },
   {
      "name":"Hungary",
      "id":"HU"
   },
   {
      "name":"Iceland",
      "id":"IS"
   },
   {
      "name":"India",
      "id":"IN"
   },
   {
      "name":"Indonesia",
      "id":"ID"
   },
   {
      "name":"Iran, Islamic Republic Of",
      "id":"IR"
   },
   {
      "name":"Iraq",
      "id":"IQ"
   },
   {
      "name":"Ireland",
      "id":"IE"
   },
   {
      "name":"Isle of Man",
      "id":"IM"
   },
   {
      "name":"Israel",
      "id":"IL"
   },
   {
      "name":"Italy",
      "id":"IT"
   },
   {
      "name":"Jamaica",
      "id":"JM"
   },
   {
      "name":"Japan",
      "id":"JP"
   }
]